<?xml version="1.0" encoding="utf-8"?>
<Return xmlns="http://www.irs.gov/efile" xmlns:xsi="http://www.w3.org/2001/XMLSchema-instance" returnVersion="2016v3.0" xsi:schemaLocation="http://www.irs.gov/efile">
  <ReturnHeader binaryAttachmentCnt="0">
    <ReturnTs>2017-05-15T11:17:36-07:00</ReturnTs>
    <TaxPeriodEndDt>2016-12-31</TaxPeriodEndDt>
    <PreparerFirmGrp>
      <PreparerFirmName>
        <BusinessNameLine1Txt>LaukaMcGuire &amp; Associates PC</BusinessNameLine1Txt>
      </PreparerFirmName>
      <PreparerUSAddress>
        <AddressLine1Txt>3511 SE Milwaukie Ave</AddressLine1Txt>
        <CityNm>Portland</CityNm>
        <StateAbbreviationCd>OR</StateAbbreviationCd>
        <ZIPCd>97202</ZIPCd>
      </PreparerUSAddress>
    </PreparerFirmGrp>
    <ReturnTypeCd>990</ReturnTypeCd>
    <TaxPeriodBeginDt>2016-01-01</TaxPeriodBeginDt>
    <Filer>
      <EIN>930630376</EIN>
      <BusinessName>
        <BusinessNameLine1Txt>Delphi Schools Inc</BusinessNameLine1Txt>
      </BusinessName>
      <BusinessNameControlTxt>DELP</BusinessNameControlTxt>
      <PhoneNum>5038433521</PhoneNum>
      <USAddress>
        <AddressLine1Txt>20950 SW Rock Creek Rd</AddressLine1Txt>
        <CityNm>Sheridan</CityNm>
        <StateAbbreviationCd>OR</StateAbbreviationCd>
        <ZIPCd>97378</ZIPCd>
      </USAddress>
    </Filer>
    <BusinessOfficerGrp>
      <PersonNm>Gregory Ott</PersonNm>
      <PersonTitleTxt>President</PersonTitleTxt>
      <SignatureDt>2017-05-15</SignatureDt>
      <DiscussWithPaidPreparerInd>true</DiscussWithPaidPreparerInd>
    </BusinessOfficerGrp>
    <PreparerPersonGrp>
      <PreparerPersonNm>Teresa L McGuire</PreparerPersonNm>
      <PTIN>P00246434</PTIN>
      <PhoneNum>5032332177</PhoneNum>
    </PreparerPersonGrp>
    <TaxYr>2016</TaxYr>
    <BuildTS>2017-02-10 21:41:12Z</BuildTS>
  </ReturnHeader>
  <ReturnData documentCnt="11">
    <IRS990 documentId="IRS990" referenceDocumentId="IRS990ScheduleO" softwareId="16000303" softwareVersionNum="2016v3.0">
      <PrincipalOfficerNm>Gregory Ott</PrincipalOfficerNm>
      <USAddress>
        <AddressLine1Txt>20950 SW Rock Creek Rd</AddressLine1Txt>
        <CityNm>Sheridan</CityNm>
        <StateAbbreviationCd>OR</StateAbbreviationCd>
        <ZIPCd>97378</ZIPCd>
      </USAddress>
      <GrossReceiptsAmt>27602353</GrossReceiptsAmt>
      <GroupReturnForAffiliatesInd>false</GroupReturnForAffiliatesInd>
      <AllAffiliatesIncludedInd>false</AllAffiliatesIncludedInd>
      <Organization501c3Ind>X</Organization501c3Ind>
      <WebsiteAddressTxt>WWW.DELPHIAN.ORG</WebsiteAddressTxt>
      <TypeOfOrganizationCorpInd>X</TypeOfOrganizationCorpInd>
      <FormationYr>1973</FormationYr>
      <LegalDomicileStateCd>OR</LegalDomicileStateCd>
      <ActivityOrMissionDesc>Develops, operates, and advises private, non-sectarian "Delphi Academy" schools owned and operated by Delphi Schools, Inc., and licenses its "Delphi Program" to schools owned and/or operated by other nonprofit tax-exempt organizations.</ActivityOrMissionDesc>
      <VotingMembersGoverningBodyCnt>13</VotingMembersGoverningBodyCnt>
      <VotingMembersIndependentCnt>6</VotingMembersIndependentCnt>
      <TotalEmployeeCnt>294</TotalEmployeeCnt>
      <TotalVolunteersCnt>18</TotalVolunteersCnt>
      <TotalGrossUBIAmt>0</TotalGrossUBIAmt>
      <PYContributionsGrantsAmt>795959</PYContributionsGrantsAmt>
      <CYContributionsGrantsAmt>9814556</CYContributionsGrantsAmt>
      <PYProgramServiceRevenueAmt>17185502</PYProgramServiceRevenueAmt>
      <CYProgramServiceRevenueAmt>15532252</CYProgramServiceRevenueAmt>
      <PYInvestmentIncomeAmt>462294</PYInvestmentIncomeAmt>
      <CYInvestmentIncomeAmt>439195</CYInvestmentIncomeAmt>
      <PYOtherRevenueAmt>161484</PYOtherRevenueAmt>
      <CYOtherRevenueAmt>205110</CYOtherRevenueAmt>
      <PYTotalRevenueAmt>18605239</PYTotalRevenueAmt>
      <CYTotalRevenueAmt>25991113</CYTotalRevenueAmt>
      <PYGrantsAndSimilarPaidAmt>2020631</PYGrantsAndSimilarPaidAmt>
      <CYGrantsAndSimilarPaidAmt>2731553</CYGrantsAndSimilarPaidAmt>
      <CYBenefitsPaidToMembersAmt>0</CYBenefitsPaidToMembersAmt>
      <PYSalariesCompEmpBnftPaidAmt>8252470</PYSalariesCompEmpBnftPaidAmt>
      <CYSalariesCompEmpBnftPaidAmt>7883387</CYSalariesCompEmpBnftPaidAmt>
      <CYTotalProfFndrsngExpnsAmt>0</CYTotalProfFndrsngExpnsAmt>
      <CYTotalFundraisingExpenseAmt>152010</CYTotalFundraisingExpenseAmt>
      <PYOtherExpensesAmt>6764872</PYOtherExpensesAmt>
      <CYOtherExpensesAmt>6037731</CYOtherExpensesAmt>
      <PYTotalExpensesAmt>17037973</PYTotalExpensesAmt>
      <CYTotalExpensesAmt>16652671</CYTotalExpensesAmt>
      <PYRevenuesLessExpensesAmt>1567266</PYRevenuesLessExpensesAmt>
      <CYRevenuesLessExpensesAmt>9338442</CYRevenuesLessExpensesAmt>
      <TotalAssetsBOYAmt>29696417</TotalAssetsBOYAmt>
      <TotalAssetsEOYAmt>38192922</TotalAssetsEOYAmt>
      <TotalLiabilitiesBOYAmt>10121335</TotalLiabilitiesBOYAmt>
      <TotalLiabilitiesEOYAmt>8985266</TotalLiabilitiesEOYAmt>
      <NetAssetsOrFundBalancesBOYAmt>19575082</NetAssetsOrFundBalancesBOYAmt>
      <NetAssetsOrFundBalancesEOYAmt>29207656</NetAssetsOrFundBalancesEOYAmt>
      <MissionDesc>Develops, operates, and advises private, non-sectarian "Delphi Academy" schools owned and operated by Delphi Schools, Inc., and licenses its "Delphi Program" to schools owned and/or operated by other nonprofit tax-exempt organizations.</MissionDesc>
      <SignificantNewProgramSrvcInd>false</SignificantNewProgramSrvcInd>
      <SignificantChangeInd>false</SignificantChangeInd>
      <ExpenseAmt>15725884</ExpenseAmt>
      <GrantAmt>2731553</GrantAmt>
      <RevenueAmt>15532252</RevenueAmt>
      <Desc>Delphi Schools Inc develops, operates, and advises private, non-sectarian Delphi Academy schools owned and operated by Delphi Schools, Inc., and licenses the Delphi Program to schools owned and/or operated by other nonprofit tax-exempt organizations, in conjunction with Delphi Schools, Inc.s Delphi Program comprised of its: (i) educational curriculum, syllabi, and supporting implementation advice for the education of students in preschool/kindergarten through high school and beyond; (ii) educational publications; and (iii) Delphi trademarks and service marks. Delphi Schools, Inc., currently owns and operates two such schools: a boarding school located in Sheridan, Oregon (The Delphian School); and a day school located in Los Angeles, California (Delphi Academy of Los Angeles). Delphi Schools Inc. owned and operated a day school located in Santa Monica, California (Delphi Academy of Santa Monica) through June 2016 when the school was closed, and Delphi Academy of Campbell through May 9, 2016 when it was spun-off into its own nonprofit organization. Delphi Schools, Inc. also licenses three schools owned and/or operated by other nonprofit tax-exempt organizations: a day school located in Milton, Massachusetts (Delphi Academy of Boston); a day school located in Clearwater, Florida (Delphi Academy of Florida); and a day school located in Campbell, California (Delphi Academy of Campbell).</Desc>
      <TotalProgramServiceExpensesAmt>15725884</TotalProgramServiceExpensesAmt>
      <DescribedInSection501c3Ind referenceDocumentId="IRS990ScheduleA">true</DescribedInSection501c3Ind>
      <ScheduleBRequiredInd referenceDocumentId="IRS990ScheduleB">true</ScheduleBRequiredInd>
      <PoliticalCampaignActyInd>false</PoliticalCampaignActyInd>
      <LobbyingActivitiesInd>false</LobbyingActivitiesInd>
      <SubjectToProxyTaxInd>false</SubjectToProxyTaxInd>
      <DonorAdvisedFundInd referenceDocumentId="IRS990ScheduleD">true</DonorAdvisedFundInd>
      <ConservationEasementsInd referenceDocumentId="IRS990ScheduleD">false</ConservationEasementsInd>
      <CollectionsOfArtInd referenceDocumentId="IRS990ScheduleD">false</CollectionsOfArtInd>
      <CreditCounselingInd referenceDocumentId="IRS990ScheduleD">false</CreditCounselingInd>
      <TempOrPermanentEndowmentsInd referenceDocumentId="IRS990ScheduleD">true</TempOrPermanentEndowmentsInd>
      <ReportLandBuildingEquipmentInd referenceDocumentId="IRS990ScheduleD">true</ReportLandBuildingEquipmentInd>
      <ReportInvestmentsOtherSecInd referenceDocumentId="IRS990ScheduleD">false</ReportInvestmentsOtherSecInd>
      <ReportProgramRelatedInvstInd referenceDocumentId="IRS990ScheduleD">false</ReportProgramRelatedInvstInd>
      <ReportOtherAssetsInd referenceDocumentId="IRS990ScheduleD">false</ReportOtherAssetsInd>
      <ReportOtherLiabilitiesInd referenceDocumentId="IRS990ScheduleD">true</ReportOtherLiabilitiesInd>
      <IncludeFIN48FootnoteInd referenceDocumentId="IRS990ScheduleD">false</IncludeFIN48FootnoteInd>
      <IndependentAuditFinclStmtInd referenceDocumentId="IRS990ScheduleD">false</IndependentAuditFinclStmtInd>
      <ConsolidatedAuditFinclStmtInd referenceDocumentId="IRS990ScheduleD">false</ConsolidatedAuditFinclStmtInd>
      <SchoolOperatingInd referenceDocumentId="IRS990ScheduleE">true</SchoolOperatingInd>
      <ForeignOfficeInd>false</ForeignOfficeInd>
      <ForeignActivitiesInd>false</ForeignActivitiesInd>
      <MoreThan5000KToOrgInd>false</MoreThan5000KToOrgInd>
      <MoreThan5000KToIndividualsInd>false</MoreThan5000KToIndividualsInd>
      <ProfessionalFundraisingInd referenceDocumentId="IRS990ScheduleG">false</ProfessionalFundraisingInd>
      <FundraisingActivitiesInd referenceDocumentId="IRS990ScheduleG">true</FundraisingActivitiesInd>
      <GamingActivitiesInd referenceDocumentId="IRS990ScheduleG">false</GamingActivitiesInd>
      <OperateHospitalInd>false</OperateHospitalInd>
      <GrantsToOrganizationsInd referenceDocumentId="IRS990ScheduleI">true</GrantsToOrganizationsInd>
      <GrantsToIndividualsInd referenceDocumentId="IRS990ScheduleI">true</GrantsToIndividualsInd>
      <ScheduleJRequiredInd referenceDocumentId="IRS990ScheduleJ">true</ScheduleJRequiredInd>
      <TaxExemptBondsInd referenceDocumentId="IRS990ScheduleK.1">true</TaxExemptBondsInd>
      <InvestTaxExemptBondsInd>false</InvestTaxExemptBondsInd>
      <EscrowAccountInd>false</EscrowAccountInd>
      <OnBehalfOfIssuerInd>false</OnBehalfOfIssuerInd>
      <EngagedInExcessBenefitTransInd referenceDocumentId="IRS990ScheduleL">false</EngagedInExcessBenefitTransInd>
      <PYExcessBenefitTransInd referenceDocumentId="IRS990ScheduleL">false</PYExcessBenefitTransInd>
      <LoanOutstandingInd referenceDocumentId="IRS990ScheduleL">false</LoanOutstandingInd>
      <GrantToRelatedPersonInd referenceDocumentId="IRS990ScheduleL">false</GrantToRelatedPersonInd>
      <BusinessRlnWithOrgMemInd referenceDocumentId="IRS990ScheduleL">false</BusinessRlnWithOrgMemInd>
      <BusinessRlnWithFamMemInd referenceDocumentId="IRS990ScheduleL">true</BusinessRlnWithFamMemInd>
      <BusinessRlnWithOfficerEntInd referenceDocumentId="IRS990ScheduleL">false</BusinessRlnWithOfficerEntInd>
      <DeductibleNonCashContriInd>false</DeductibleNonCashContriInd>
      <DeductibleArtContributionInd>false</DeductibleArtContributionInd>
      <TerminateOperationsInd>false</TerminateOperationsInd>
      <PartialLiquidationInd>false</PartialLiquidationInd>
      <DisregardedEntityInd>false</DisregardedEntityInd>
      <RelatedEntityInd>false</RelatedEntityInd>
      <RelatedOrganizationCtrlEntInd>false</RelatedOrganizationCtrlEntInd>
      <TransactionWithControlEntInd>false</TransactionWithControlEntInd>
      <TrnsfrExmptNonChrtblRltdOrgInd>false</TrnsfrExmptNonChrtblRltdOrgInd>
      <ActivitiesConductedPrtshpInd>false</ActivitiesConductedPrtshpInd>
      <ScheduleORequiredInd>true</ScheduleORequiredInd>
      <IRPDocumentCnt>61</IRPDocumentCnt>
      <IRPDocumentW2GCnt>0</IRPDocumentW2GCnt>
      <BackupWthldComplianceInd>true</BackupWthldComplianceInd>
      <EmployeeCnt>294</EmployeeCnt>
      <EmploymentTaxReturnsFiledInd>true</EmploymentTaxReturnsFiledInd>
      <UnrelatedBusIncmOverLimitInd>false</UnrelatedBusIncmOverLimitInd>
      <Form990TFiledInd>false</Form990TFiledInd>
      <ForeignFinancialAccountInd>false</ForeignFinancialAccountInd>
      <ProhibitedTaxShelterTransInd>false</ProhibitedTaxShelterTransInd>
      <TaxablePartyNotificationInd>false</TaxablePartyNotificationInd>
      <NondeductibleContributionsInd>false</NondeductibleContributionsInd>
      <QuidProQuoContributionsInd>false</QuidProQuoContributionsInd>
      <Form8282PropertyDisposedOfInd>false</Form8282PropertyDisposedOfInd>
      <Form8282FiledCnt>0</Form8282FiledCnt>
      <RcvFndsToPayPrsnlBnftCntrctInd>false</RcvFndsToPayPrsnlBnftCntrctInd>
      <PayPremiumsPrsnlBnftCntrctInd>false</PayPremiumsPrsnlBnftCntrctInd>
      <Form8899Filedind>false</Form8899Filedind>
      <Form1098CFiledInd>false</Form1098CFiledInd>
      <DAFExcessBusinessHoldingsInd>false</DAFExcessBusinessHoldingsInd>
      <TaxableDistributionsInd>false</TaxableDistributionsInd>
      <DistributionToDonorInd>false</DistributionToDonorInd>
      <OrgFiledInLieuOfForm1041Ind>false</OrgFiledInLieuOfForm1041Ind>
      <LicensedMoreThanOneStateInd>false</LicensedMoreThanOneStateInd>
      <IndoorTanningServicesInd>false</IndoorTanningServicesInd>
      <InfoInScheduleOPartVIInd>X</InfoInScheduleOPartVIInd>
      <GoverningBodyVotingMembersCnt>13</GoverningBodyVotingMembersCnt>
      <IndependentVotingMemberCnt>6</IndependentVotingMemberCnt>
      <FamilyOrBusinessRlnInd>true</FamilyOrBusinessRlnInd>
      <DelegationOfMgmtDutiesInd>false</DelegationOfMgmtDutiesInd>
      <ChangeToOrgDocumentsInd>false</ChangeToOrgDocumentsInd>
      <MaterialDiversionOrMisuseInd>false</MaterialDiversionOrMisuseInd>
      <MembersOrStockholdersInd>false</MembersOrStockholdersInd>
      <ElectionOfBoardMembersInd>false</ElectionOfBoardMembersInd>
      <DecisionsSubjectToApprovaInd>false</DecisionsSubjectToApprovaInd>
      <MinutesOfGoverningBodyInd>true</MinutesOfGoverningBodyInd>
      <MinutesOfCommitteesInd>true</MinutesOfCommitteesInd>
      <OfficerMailingAddressInd>false</OfficerMailingAddressInd>
      <LocalChaptersInd>true</LocalChaptersInd>
      <PoliciesReferenceChaptersInd>true</PoliciesReferenceChaptersInd>
      <Form990ProvidedToGvrnBodyInd>true</Form990ProvidedToGvrnBodyInd>
      <ConflictOfInterestPolicyInd>true</ConflictOfInterestPolicyInd>
      <AnnualDisclosureCoveredPrsnInd>true</AnnualDisclosureCoveredPrsnInd>
      <RegularMonitoringEnfrcInd>true</RegularMonitoringEnfrcInd>
      <WhistleblowerPolicyInd>true</WhistleblowerPolicyInd>
      <DocumentRetentionPolicyInd>true</DocumentRetentionPolicyInd>
      <CompensationProcessCEOInd>true</CompensationProcessCEOInd>
      <CompensationProcessOtherInd>true</CompensationProcessOtherInd>
      <InvestmentInJointVentureInd>false</InvestmentInJointVentureInd>
      <StatesWhereCopyOfReturnIsFldCd>OR</StatesWhereCopyOfReturnIsFldCd>
      <UponRequestInd>X</UponRequestInd>
      <BooksInCareOfDetail>
        <PersonNm>Jeanne McKevitt</PersonNm>
        <PhoneNum>5038433521</PhoneNum>
        <USAddress>
          <AddressLine1Txt>20950 SW Rock Creek Road</AddressLine1Txt>
          <CityNm>Sheridan</CityNm>
          <StateAbbreviationCd>OR</StateAbbreviationCd>
          <ZIPCd>97378</ZIPCd>
        </USAddress>
      </BooksInCareOfDetail>
      <Form990PartVIISectionAGrp>
        <PersonNm>Gregory Ott</PersonNm>
        <TitleTxt>President</TitleTxt>
        <AverageHoursPerWeekRt>50.00</AverageHoursPerWeekRt>
        <AverageHoursPerWeekRltdOrgRt>0.00</AverageHoursPerWeekRltdOrgRt>
        <IndividualTrusteeOrDirectorInd>X</IndividualTrusteeOrDirectorInd>
        <OfficerInd>X</OfficerInd>
        <ReportableCompFromOrgAmt>240014</ReportableCompFromOrgAmt>
        <ReportableCompFromRltdOrgAmt>0</ReportableCompFromRltdOrgAmt>
        <OtherCompensationAmt>21682</OtherCompensationAmt>
      </Form990PartVIISectionAGrp>
      <Form990PartVIISectionAGrp>
        <PersonNm>Rosemary Didear</PersonNm>
        <TitleTxt>Vice President</TitleTxt>
        <AverageHoursPerWeekRt>50.00</AverageHoursPerWeekRt>
        <AverageHoursPerWeekRltdOrgRt>0.00</AverageHoursPerWeekRltdOrgRt>
        <IndividualTrusteeOrDirectorInd>X</IndividualTrusteeOrDirectorInd>
        <OfficerInd>X</OfficerInd>
        <ReportableCompFromOrgAmt>108536</ReportableCompFromOrgAmt>
        <ReportableCompFromRltdOrgAmt>0</ReportableCompFromRltdOrgAmt>
        <OtherCompensationAmt>5827</OtherCompensationAmt>
      </Form990PartVIISectionAGrp>
      <Form990PartVIISectionAGrp>
        <PersonNm>Alan Rothe</PersonNm>
        <TitleTxt>Exec Vice Pres</TitleTxt>
        <AverageHoursPerWeekRt>50.00</AverageHoursPerWeekRt>
        <AverageHoursPerWeekRltdOrgRt>0.00</AverageHoursPerWeekRltdOrgRt>
        <IndividualTrusteeOrDirectorInd>X</IndividualTrusteeOrDirectorInd>
        <OfficerInd>X</OfficerInd>
        <ReportableCompFromOrgAmt>160643</ReportableCompFromOrgAmt>
        <ReportableCompFromRltdOrgAmt>0</ReportableCompFromRltdOrgAmt>
        <OtherCompensationAmt>21876</OtherCompensationAmt>
      </Form990PartVIISectionAGrp>
      <Form990PartVIISectionAGrp>
        <PersonNm>John Nosko</PersonNm>
        <TitleTxt>Sec &amp; Treasurer</TitleTxt>
        <AverageHoursPerWeekRt>50.00</AverageHoursPerWeekRt>
        <AverageHoursPerWeekRltdOrgRt>0.00</AverageHoursPerWeekRltdOrgRt>
        <IndividualTrusteeOrDirectorInd>X</IndividualTrusteeOrDirectorInd>
        <OfficerInd>X</OfficerInd>
        <ReportableCompFromOrgAmt>153580</ReportableCompFromOrgAmt>
        <ReportableCompFromRltdOrgAmt>0</ReportableCompFromRltdOrgAmt>
        <OtherCompensationAmt>16155</OtherCompensationAmt>
      </Form990PartVIISectionAGrp>
      <Form990PartVIISectionAGrp>
        <PersonNm>Trevor Ott</PersonNm>
        <TitleTxt>Head of School</TitleTxt>
        <AverageHoursPerWeekRt>50.00</AverageHoursPerWeekRt>
        <AverageHoursPerWeekRltdOrgRt>0.00</AverageHoursPerWeekRltdOrgRt>
        <IndividualTrusteeOrDirectorInd>X</IndividualTrusteeOrDirectorInd>
        <ReportableCompFromOrgAmt>92177</ReportableCompFromOrgAmt>
        <ReportableCompFromRltdOrgAmt>0</ReportableCompFromRltdOrgAmt>
        <OtherCompensationAmt>50691</OtherCompensationAmt>
      </Form990PartVIISectionAGrp>
      <Form990PartVIISectionAGrp>
        <PersonNm>Arwen Dayton</PersonNm>
        <TitleTxt>Director</TitleTxt>
        <AverageHoursPerWeekRt>1.00</AverageHoursPerWeekRt>
        <AverageHoursPerWeekRltdOrgRt>0.00</AverageHoursPerWeekRltdOrgRt>
        <IndividualTrusteeOrDirectorInd>X</IndividualTrusteeOrDirectorInd>
        <ReportableCompFromOrgAmt>0</ReportableCompFromOrgAmt>
        <ReportableCompFromRltdOrgAmt>0</ReportableCompFromRltdOrgAmt>
        <OtherCompensationAmt>0</OtherCompensationAmt>
      </Form990PartVIISectionAGrp>
      <Form990PartVIISectionAGrp>
        <PersonNm>Todd Kugler</PersonNm>
        <TitleTxt>Director</TitleTxt>
        <AverageHoursPerWeekRt>1.00</AverageHoursPerWeekRt>
        <AverageHoursPerWeekRltdOrgRt>0.00</AverageHoursPerWeekRltdOrgRt>
        <IndividualTrusteeOrDirectorInd>X</IndividualTrusteeOrDirectorInd>
        <ReportableCompFromOrgAmt>0</ReportableCompFromOrgAmt>
        <ReportableCompFromRltdOrgAmt>0</ReportableCompFromRltdOrgAmt>
        <OtherCompensationAmt>0</OtherCompensationAmt>
      </Form990PartVIISectionAGrp>
      <Form990PartVIISectionAGrp>
        <PersonNm>Dave Hendry</PersonNm>
        <TitleTxt>Director</TitleTxt>
        <AverageHoursPerWeekRt>1.00</AverageHoursPerWeekRt>
        <AverageHoursPerWeekRltdOrgRt>0.00</AverageHoursPerWeekRltdOrgRt>
        <IndividualTrusteeOrDirectorInd>X</IndividualTrusteeOrDirectorInd>
        <ReportableCompFromOrgAmt>0</ReportableCompFromOrgAmt>
        <ReportableCompFromRltdOrgAmt>0</ReportableCompFromRltdOrgAmt>
        <OtherCompensationAmt>0</OtherCompensationAmt>
      </Form990PartVIISectionAGrp>
      <Form990PartVIISectionAGrp>
        <PersonNm>Cheryl R Berman</PersonNm>
        <TitleTxt>Director</TitleTxt>
        <AverageHoursPerWeekRt>1.00</AverageHoursPerWeekRt>
        <AverageHoursPerWeekRltdOrgRt>0.00</AverageHoursPerWeekRltdOrgRt>
        <IndividualTrusteeOrDirectorInd>X</IndividualTrusteeOrDirectorInd>
        <ReportableCompFromOrgAmt>0</ReportableCompFromOrgAmt>
        <ReportableCompFromRltdOrgAmt>0</ReportableCompFromRltdOrgAmt>
        <OtherCompensationAmt>0</OtherCompensationAmt>
      </Form990PartVIISectionAGrp>
      <Form990PartVIISectionAGrp>
        <PersonNm>Steve Anderson</PersonNm>
        <TitleTxt>Director</TitleTxt>
        <AverageHoursPerWeekRt>1.00</AverageHoursPerWeekRt>
        <AverageHoursPerWeekRltdOrgRt>0.00</AverageHoursPerWeekRltdOrgRt>
        <IndividualTrusteeOrDirectorInd>X</IndividualTrusteeOrDirectorInd>
        <ReportableCompFromOrgAmt>0</ReportableCompFromOrgAmt>
        <ReportableCompFromRltdOrgAmt>0</ReportableCompFromRltdOrgAmt>
        <OtherCompensationAmt>0</OtherCompensationAmt>
      </Form990PartVIISectionAGrp>
      <Form990PartVIISectionAGrp>
        <PersonNm>Shon Holyfield</PersonNm>
        <TitleTxt>Director</TitleTxt>
        <AverageHoursPerWeekRt>1.00</AverageHoursPerWeekRt>
        <AverageHoursPerWeekRltdOrgRt>0.00</AverageHoursPerWeekRltdOrgRt>
        <IndividualTrusteeOrDirectorInd>X</IndividualTrusteeOrDirectorInd>
        <ReportableCompFromOrgAmt>0</ReportableCompFromOrgAmt>
        <ReportableCompFromRltdOrgAmt>0</ReportableCompFromRltdOrgAmt>
        <OtherCompensationAmt>0</OtherCompensationAmt>
      </Form990PartVIISectionAGrp>
      <Form990PartVIISectionAGrp>
        <PersonNm>Cleman Agami</PersonNm>
        <TitleTxt>Director</TitleTxt>
        <AverageHoursPerWeekRt>1.00</AverageHoursPerWeekRt>
        <AverageHoursPerWeekRltdOrgRt>0.00</AverageHoursPerWeekRltdOrgRt>
        <IndividualTrusteeOrDirectorInd>X</IndividualTrusteeOrDirectorInd>
        <ReportableCompFromOrgAmt>0</ReportableCompFromOrgAmt>
        <ReportableCompFromRltdOrgAmt>0</ReportableCompFromRltdOrgAmt>
        <OtherCompensationAmt>0</OtherCompensationAmt>
      </Form990PartVIISectionAGrp>
      <Form990PartVIISectionAGrp>
        <PersonNm>Christopher Alen Nosko</PersonNm>
        <TitleTxt>Director</TitleTxt>
        <AverageHoursPerWeekRt>1.00</AverageHoursPerWeekRt>
        <AverageHoursPerWeekRltdOrgRt>0.00</AverageHoursPerWeekRltdOrgRt>
        <IndividualTrusteeOrDirectorInd>X</IndividualTrusteeOrDirectorInd>
        <ReportableCompFromOrgAmt>0</ReportableCompFromOrgAmt>
        <ReportableCompFromRltdOrgAmt>0</ReportableCompFromRltdOrgAmt>
        <OtherCompensationAmt>0</OtherCompensationAmt>
      </Form990PartVIISectionAGrp>
      <Form990PartVIISectionAGrp>
        <PersonNm>Suzan Ott</PersonNm>
        <TitleTxt>Assist Secrtry</TitleTxt>
        <AverageHoursPerWeekRt>1.00</AverageHoursPerWeekRt>
        <AverageHoursPerWeekRltdOrgRt>0.00</AverageHoursPerWeekRltdOrgRt>
        <OfficerInd>X</OfficerInd>
        <ReportableCompFromOrgAmt>1419</ReportableCompFromOrgAmt>
        <ReportableCompFromRltdOrgAmt>0</ReportableCompFromRltdOrgAmt>
        <OtherCompensationAmt>0</OtherCompensationAmt>
      </Form990PartVIISectionAGrp>
      <TotalReportableCompFromOrgAmt>756369</TotalReportableCompFromOrgAmt>
      <TotalOtherCompensationAmt>116231</TotalOtherCompensationAmt>
      <IndivRcvdGreaterThan100KCnt>4</IndivRcvdGreaterThan100KCnt>
      <FormerOfcrEmployeesListedInd>false</FormerOfcrEmployeesListedInd>
      <TotalCompGreaterThan150KInd>true</TotalCompGreaterThan150KInd>
      <CompensationFromOtherSrcsInd>false</CompensationFromOtherSrcsInd>
      <ContractorCompensationGrp>
        <ContractorName>
          <BusinessName>
            <BusinessNameLine1Txt>Suite 4 Rachel Karl</BusinessNameLine1Txt>
          </BusinessName>
        </ContractorName>
        <ContractorAddress>
          <USAddress>
            <AddressLine1Txt>410 NE 3rd St Suite 4</AddressLine1Txt>
            <CityNm>McMinnville</CityNm>
            <StateAbbreviationCd>OR</StateAbbreviationCd>
            <ZIPCd>97128</ZIPCd>
          </USAddress>
        </ContractorAddress>
        <ServicesDesc>Development &amp; Media</ServicesDesc>
        <CompensationAmt>141836</CompensationAmt>
      </ContractorCompensationGrp>
      <CntrctRcvdGreaterThan100KCnt>1</CntrctRcvdGreaterThan100KCnt>
      <FundraisingAmt>32933</FundraisingAmt>
      <AllOtherContributionsAmt>9781623</AllOtherContributionsAmt>
      <NoncashContributionsAmt>8966</NoncashContributionsAmt>
      <TotalContributionsAmt>9814556</TotalContributionsAmt>
      <ProgramServiceRevenueGrp>
        <Desc>BOARDING FEES</Desc>
        <BusinessCd>611600</BusinessCd>
        <TotalRevenueColumnAmt>4514383</TotalRevenueColumnAmt>
        <RelatedOrExemptFuncIncomeAmt>4514383</RelatedOrExemptFuncIncomeAmt>
      </ProgramServiceRevenueGrp>
      <ProgramServiceRevenueGrp>
        <Desc>Materials</Desc>
        <BusinessCd>611600</BusinessCd>
        <TotalRevenueColumnAmt>863581</TotalRevenueColumnAmt>
        <RelatedOrExemptFuncIncomeAmt>863581</RelatedOrExemptFuncIncomeAmt>
      </ProgramServiceRevenueGrp>
      <ProgramServiceRevenueGrp>
        <Desc>TUITION</Desc>
        <BusinessCd>611600</BusinessCd>
        <TotalRevenueColumnAmt>9624538</TotalRevenueColumnAmt>
        <RelatedOrExemptFuncIncomeAmt>9624538</RelatedOrExemptFuncIncomeAmt>
      </ProgramServiceRevenueGrp>
      <ProgramServiceRevenueGrp>
        <Desc>YEARBOOK &amp; PROGRAM FEES</Desc>
        <BusinessCd>611600</BusinessCd>
        <TotalRevenueColumnAmt>529750</TotalRevenueColumnAmt>
        <RelatedOrExemptFuncIncomeAmt>529750</RelatedOrExemptFuncIncomeAmt>
      </ProgramServiceRevenueGrp>
      <TotalProgramServiceRevenueAmt>15532252</TotalProgramServiceRevenueAmt>
      <InvestmentIncomeGrp>
        <TotalRevenueColumnAmt>235621</TotalRevenueColumnAmt>
        <ExclusionAmt>235621</ExclusionAmt>
      </InvestmentIncomeGrp>
      <IncmFromInvestBondProceedsGrp>
        <TotalRevenueColumnAmt>0</TotalRevenueColumnAmt>
      </IncmFromInvestBondProceedsGrp>
      <RoyaltiesRevenueGrp>
        <TotalRevenueColumnAmt>0</TotalRevenueColumnAmt>
      </RoyaltiesRevenueGrp>
      <GrossRentsGrp>
        <RealAmt>100923</RealAmt>
      </GrossRentsGrp>
      <RentalIncomeOrLossGrp>
        <RealAmt>100923</RealAmt>
      </RentalIncomeOrLossGrp>
      <NetRentalIncomeOrLossGrp>
        <TotalRevenueColumnAmt>100923</TotalRevenueColumnAmt>
        <ExclusionAmt>100923</ExclusionAmt>
      </NetRentalIncomeOrLossGrp>
      <GrossAmountSalesAssetsGrp>
        <SecuritiesAmt>1612774</SecuritiesAmt>
        <OtherAmt>130833</OtherAmt>
      </GrossAmountSalesAssetsGrp>
      <LessCostOthBasisSalesExpnssGrp>
        <SecuritiesAmt>1540033</SecuritiesAmt>
      </LessCostOthBasisSalesExpnssGrp>
      <GainOrLossGrp>
        <SecuritiesAmt>72741</SecuritiesAmt>
        <OtherAmt>130833</OtherAmt>
      </GainOrLossGrp>
      <NetGainOrLossInvestmentsGrp>
        <TotalRevenueColumnAmt>203574</TotalRevenueColumnAmt>
        <RelatedOrExemptFuncIncomeAmt>203574</RelatedOrExemptFuncIncomeAmt>
      </NetGainOrLossInvestmentsGrp>
      <ContriRptFundraisingEventAmt>32933</ContriRptFundraisingEventAmt>
      <FundraisingDirectExpensesAmt>2759</FundraisingDirectExpensesAmt>
      <NetIncmFromFundraisingEvtGrp>
        <TotalRevenueColumnAmt>-2759</TotalRevenueColumnAmt>
        <ExclusionAmt>-2759</ExclusionAmt>
      </NetIncmFromFundraisingEvtGrp>
      <NetIncomeFromGamingGrp>
        <TotalRevenueColumnAmt>0</TotalRevenueColumnAmt>
      </NetIncomeFromGamingGrp>
      <GrossSalesOfInventoryAmt>144544</GrossSalesOfInventoryAmt>
      <CostOfGoodsSoldAmt>68448</CostOfGoodsSoldAmt>
      <NetIncomeOrLossGrp>
        <TotalRevenueColumnAmt>76096</TotalRevenueColumnAmt>
        <ExclusionAmt>76096</ExclusionAmt>
      </NetIncomeOrLossGrp>
      <OtherRevenueMiscGrp>
        <Desc>FINANCE CHARGES</Desc>
        <BusinessCd>525990</BusinessCd>
        <TotalRevenueColumnAmt>12160</TotalRevenueColumnAmt>
        <ExclusionAmt>12160</ExclusionAmt>
      </OtherRevenueMiscGrp>
      <OtherRevenueMiscGrp>
        <Desc>Scrap Material Sales</Desc>
        <BusinessCd>900099</BusinessCd>
        <TotalRevenueColumnAmt>18690</TotalRevenueColumnAmt>
        <ExclusionAmt>18690</ExclusionAmt>
      </OtherRevenueMiscGrp>
      <OtherRevenueTotalAmt>30850</OtherRevenueTotalAmt>
      <TotalRevenueGrp>
        <TotalRevenueColumnAmt>25991113</TotalRevenueColumnAmt>
        <RelatedOrExemptFuncIncomeAmt>15735826</RelatedOrExemptFuncIncomeAmt>
        <ExclusionAmt>440731</ExclusionAmt>
      </TotalRevenueGrp>
      <GrantsToDomesticOrgsGrp>
        <TotalAmt>375160</TotalAmt>
        <ProgramServicesAmt>375160</ProgramServicesAmt>
      </GrantsToDomesticOrgsGrp>
      <GrantsToDomesticIndividualsGrp>
        <TotalAmt>2356393</TotalAmt>
        <ProgramServicesAmt>2356393</ProgramServicesAmt>
      </GrantsToDomesticIndividualsGrp>
      <ForeignGrantsGrp>
        <TotalAmt>0</TotalAmt>
      </ForeignGrantsGrp>
      <BenefitsToMembersGrp>
        <TotalAmt>0</TotalAmt>
      </BenefitsToMembersGrp>
      <CompCurrentOfcrDirectorsGrp>
        <TotalAmt>754949</TotalAmt>
        <ProgramServicesAmt>296780</ProgramServicesAmt>
        <ManagementAndGeneralAmt>349633</ManagementAndGeneralAmt>
        <FundraisingAmt>108536</FundraisingAmt>
      </CompCurrentOfcrDirectorsGrp>
      <CompDisqualPersonsGrp>
        <TotalAmt>0</TotalAmt>
      </CompDisqualPersonsGrp>
      <OtherSalariesAndWagesGrp>
        <TotalAmt>6077679</TotalAmt>
        <ProgramServicesAmt>5911888</ProgramServicesAmt>
        <ManagementAndGeneralAmt>151390</ManagementAndGeneralAmt>
        <FundraisingAmt>14401</FundraisingAmt>
      </OtherSalariesAndWagesGrp>
      <PensionPlanContributionsGrp>
        <TotalAmt>0</TotalAmt>
      </PensionPlanContributionsGrp>
      <OtherEmployeeBenefitsGrp>
        <TotalAmt>531912</TotalAmt>
        <ProgramServicesAmt>514400</ProgramServicesAmt>
        <ManagementAndGeneralAmt>10774</ManagementAndGeneralAmt>
        <FundraisingAmt>6738</FundraisingAmt>
      </OtherEmployeeBenefitsGrp>
      <PayrollTaxesGrp>
        <TotalAmt>518847</TotalAmt>
        <ProgramServicesAmt>480676</ProgramServicesAmt>
        <ManagementAndGeneralAmt>37115</ManagementAndGeneralAmt>
        <FundraisingAmt>1056</FundraisingAmt>
      </PayrollTaxesGrp>
      <FeesForServicesManagementGrp>
        <TotalAmt>0</TotalAmt>
      </FeesForServicesManagementGrp>
      <FeesForServicesLegalGrp>
        <TotalAmt>0</TotalAmt>
      </FeesForServicesLegalGrp>
      <FeesForServicesAccountingGrp>
        <TotalAmt>0</TotalAmt>
      </FeesForServicesAccountingGrp>
      <FeesForServicesLobbyingGrp>
        <TotalAmt>0</TotalAmt>
      </FeesForServicesLobbyingGrp>
      <FeesForServicesProfFundraising>
        <TotalAmt>0</TotalAmt>
      </FeesForServicesProfFundraising>
      <FeesForSrvcInvstMgmntFeesGrp>
        <TotalAmt>0</TotalAmt>
      </FeesForSrvcInvstMgmntFeesGrp>
      <FeesForServicesOtherGrp>
        <TotalAmt>697129</TotalAmt>
        <ProgramServicesAmt>566100</ProgramServicesAmt>
        <ManagementAndGeneralAmt>131029</ManagementAndGeneralAmt>
      </FeesForServicesOtherGrp>
      <AdvertisingGrp>
        <TotalAmt>354430</TotalAmt>
        <ProgramServicesAmt>354430</ProgramServicesAmt>
      </AdvertisingGrp>
      <OfficeExpensesGrp>
        <TotalAmt>60365</TotalAmt>
        <ProgramServicesAmt>59330</ProgramServicesAmt>
        <ManagementAndGeneralAmt>1035</ManagementAndGeneralAmt>
      </OfficeExpensesGrp>
      <InformationTechnologyGrp>
        <TotalAmt>65586</TotalAmt>
        <ProgramServicesAmt>63618</ProgramServicesAmt>
        <ManagementAndGeneralAmt>1968</ManagementAndGeneralAmt>
      </InformationTechnologyGrp>
      <RoyaltiesGrp>
        <TotalAmt>0</TotalAmt>
      </RoyaltiesGrp>
      <OccupancyGrp>
        <TotalAmt>1260890</TotalAmt>
        <ProgramServicesAmt>1235149</ProgramServicesAmt>
        <ManagementAndGeneralAmt>25741</ManagementAndGeneralAmt>
      </OccupancyGrp>
      <TravelGrp>
        <TotalAmt>23310</TotalAmt>
        <ProgramServicesAmt>11654</ProgramServicesAmt>
        <ManagementAndGeneralAmt>11656</ManagementAndGeneralAmt>
      </TravelGrp>
      <PymtTravelEntrtnmntPubOfclGrp>
        <TotalAmt>0</TotalAmt>
      </PymtTravelEntrtnmntPubOfclGrp>
      <ConferencesMeetingsGrp>
        <TotalAmt>0</TotalAmt>
      </ConferencesMeetingsGrp>
      <InterestGrp>
        <TotalAmt>159477</TotalAmt>
        <ProgramServicesAmt>154693</ProgramServicesAmt>
        <ManagementAndGeneralAmt>4784</ManagementAndGeneralAmt>
      </InterestGrp>
      <PaymentsToAffiliatesGrp>
        <TotalAmt>0</TotalAmt>
      </PaymentsToAffiliatesGrp>
      <DepreciationDepletionGrp>
        <TotalAmt>892857</TotalAmt>
        <ProgramServicesAmt>875000</ProgramServicesAmt>
        <ManagementAndGeneralAmt>17857</ManagementAndGeneralAmt>
      </DepreciationDepletionGrp>
      <InsuranceGrp>
        <TotalAmt>213454</TotalAmt>
        <ProgramServicesAmt>206468</ProgramServicesAmt>
        <ManagementAndGeneralAmt>4270</ManagementAndGeneralAmt>
        <FundraisingAmt>2716</FundraisingAmt>
      </InsuranceGrp>
      <OtherExpensesGrp>
        <Desc>Food Cost</Desc>
        <TotalAmt>1136095</TotalAmt>
        <ProgramServicesAmt>1113373</ProgramServicesAmt>
        <ManagementAndGeneralAmt>22722</ManagementAndGeneralAmt>
      </OtherExpensesGrp>
      <OtherExpensesGrp>
        <Desc>Educational Expense</Desc>
        <TotalAmt>628045</TotalAmt>
        <ProgramServicesAmt>628045</ProgramServicesAmt>
      </OtherExpensesGrp>
      <OtherExpensesGrp>
        <Desc>Bank Charges</Desc>
        <TotalAmt>118353</TotalAmt>
        <ProgramServicesAmt>118353</ProgramServicesAmt>
      </OtherExpensesGrp>
      <OtherExpensesGrp>
        <Desc>Tours Expenses</Desc>
        <TotalAmt>74133</TotalAmt>
        <ProgramServicesAmt>74133</ProgramServicesAmt>
      </OtherExpensesGrp>
      <AllOtherExpensesGrp>
        <TotalAmt>353607</TotalAmt>
        <ProgramServicesAmt>330241</ProgramServicesAmt>
        <ManagementAndGeneralAmt>4803</ManagementAndGeneralAmt>
        <FundraisingAmt>18563</FundraisingAmt>
      </AllOtherExpensesGrp>
      <TotalFunctionalExpensesGrp>
        <TotalAmt>16652671</TotalAmt>
        <ProgramServicesAmt>15725884</ProgramServicesAmt>
        <ManagementAndGeneralAmt>774777</ManagementAndGeneralAmt>
        <FundraisingAmt>152010</FundraisingAmt>
      </TotalFunctionalExpensesGrp>
      <CashNonInterestBearingGrp>
        <BOYAmt>4472843</BOYAmt>
        <EOYAmt>6847358</EOYAmt>
      </CashNonInterestBearingGrp>
      <SavingsAndTempCashInvstGrp>
        <BOYAmt>5549989</BOYAmt>
        <EOYAmt>11160848</EOYAmt>
      </SavingsAndTempCashInvstGrp>
      <PledgesAndGrantsReceivableGrp>
        <EOYAmt>0</EOYAmt>
      </PledgesAndGrantsReceivableGrp>
      <AccountsReceivableGrp>
        <BOYAmt>81109</BOYAmt>
        <EOYAmt>54470</EOYAmt>
      </AccountsReceivableGrp>
      <ReceivablesFromOfficersEtcGrp>
        <EOYAmt>0</EOYAmt>
      </ReceivablesFromOfficersEtcGrp>
      <RcvblFromDisqualifiedPrsnGrp>
        <EOYAmt>0</EOYAmt>
      </RcvblFromDisqualifiedPrsnGrp>
      <OthNotesLoansReceivableNetGrp>
        <EOYAmt>0</EOYAmt>
      </OthNotesLoansReceivableNetGrp>
      <InventoriesForSaleOrUseGrp>
        <BOYAmt>34115</BOYAmt>
        <EOYAmt>29085</EOYAmt>
      </InventoriesForSaleOrUseGrp>
      <PrepaidExpensesDefrdChargesGrp>
        <BOYAmt>188038</BOYAmt>
        <EOYAmt>75767</EOYAmt>
      </PrepaidExpensesDefrdChargesGrp>
      <LandBldgEquipCostOrOtherBssAmt>24573723</LandBldgEquipCostOrOtherBssAmt>
      <LandBldgEquipAccumDeprecAmt>9573957</LandBldgEquipAccumDeprecAmt>
      <LandBldgEquipBasisNetGrp>
        <BOYAmt>14123461</BOYAmt>
        <EOYAmt>14999766</EOYAmt>
      </LandBldgEquipBasisNetGrp>
      <InvestmentsPubTradedSecGrp>
        <BOYAmt>5105310</BOYAmt>
        <EOYAmt>4949637</EOYAmt>
      </InvestmentsPubTradedSecGrp>
      <InvestmentsOtherSecuritiesGrp>
        <EOYAmt>0</EOYAmt>
      </InvestmentsOtherSecuritiesGrp>
      <InvestmentsProgramRelatedGrp>
        <EOYAmt>0</EOYAmt>
      </InvestmentsProgramRelatedGrp>
      <IntangibleAssetsGrp>
        <EOYAmt>0</EOYAmt>
      </IntangibleAssetsGrp>
      <OtherAssetsTotalGrp>
        <BOYAmt>141552</BOYAmt>
        <EOYAmt>75991</EOYAmt>
      </OtherAssetsTotalGrp>
      <TotalAssetsGrp>
        <BOYAmt>29696417</BOYAmt>
        <EOYAmt>38192922</EOYAmt>
      </TotalAssetsGrp>
      <AccountsPayableAccrExpnssGrp>
        <BOYAmt>320840</BOYAmt>
        <EOYAmt>391811</EOYAmt>
      </AccountsPayableAccrExpnssGrp>
      <DeferredRevenueGrp>
        <BOYAmt>5072482</BOYAmt>
        <EOYAmt>4553585</EOYAmt>
      </DeferredRevenueGrp>
      <MortgNotesPyblScrdInvstPropGrp>
        <BOYAmt>4532404</BOYAmt>
        <EOYAmt>3908329</EOYAmt>
      </MortgNotesPyblScrdInvstPropGrp>
      <OtherLiabilitiesGrp>
        <BOYAmt>195609</BOYAmt>
        <EOYAmt>131541</EOYAmt>
      </OtherLiabilitiesGrp>
      <TotalLiabilitiesGrp>
        <BOYAmt>10121335</BOYAmt>
        <EOYAmt>8985266</EOYAmt>
      </TotalLiabilitiesGrp>
      <OrganizationFollowsSFAS117Ind>X</OrganizationFollowsSFAS117Ind>
      <UnrestrictedNetAssetsGrp>
        <BOYAmt>17250745</BOYAmt>
        <EOYAmt>26432146</EOYAmt>
      </UnrestrictedNetAssetsGrp>
      <TemporarilyRstrNetAssetsGrp>
        <BOYAmt>824337</BOYAmt>
        <EOYAmt>1275510</EOYAmt>
      </TemporarilyRstrNetAssetsGrp>
      <PermanentlyRstrNetAssetsGrp>
        <BOYAmt>1500000</BOYAmt>
        <EOYAmt>1500000</EOYAmt>
      </PermanentlyRstrNetAssetsGrp>
      <TotalNetAssetsFundBalanceGrp>
        <BOYAmt>19575082</BOYAmt>
        <EOYAmt>29207656</EOYAmt>
      </TotalNetAssetsFundBalanceGrp>
      <TotLiabNetAssetsFundBalanceGrp>
        <BOYAmt>29696417</BOYAmt>
        <EOYAmt>38192922</EOYAmt>
      </TotLiabNetAssetsFundBalanceGrp>
      <ReconcilationRevenueExpnssAmt>9338442</ReconcilationRevenueExpnssAmt>
      <NetUnrlzdGainsLossesInvstAmt>294132</NetUnrlzdGainsLossesInvstAmt>
      <MethodOfAccountingAccrualInd>X</MethodOfAccountingAccrualInd>
      <AccountantCompileOrReviewInd>true</AccountantCompileOrReviewInd>
      <AcctCompileOrReviewBasisGrp>
        <SeparateBasisFinclStmtInd>X</SeparateBasisFinclStmtInd>
      </AcctCompileOrReviewBasisGrp>
      <FSAuditedInd>false</FSAuditedInd>
      <AuditCommitteeInd>false</AuditCommitteeInd>
      <FederalGrantAuditRequiredInd>false</FederalGrantAuditRequiredInd>
    </IRS990>
    <IRS990ScheduleA documentId="IRS990ScheduleA" softwareId="16000303" softwareVersionNum="2016v3.0">
      <SchoolInd>X</SchoolInd>
    </IRS990ScheduleA>
    <IRS990ScheduleB documentId="IRS990ScheduleB" softwareId="16000303" softwareVersionNum="2016v3.0">
      <ContributorInformationGrp>
        <ContributorNum>RESTRICTED</ContributorNum>
        <ContributorBusinessName>
          <BusinessNameLine1>RESTRICTED</BusinessNameLine1>
        </ContributorBusinessName>
        <ContributorUSAddress>
          <AddressLine1>RESTRICTED</AddressLine1>
          <AddressLine2>RESTRICTED</AddressLine2>
          <City>RESTRICTED</City>
          <State>RESTRICTED</State>
          <ZIPCode>RESTRICTED</ZIPCode>
        </ContributorUSAddress>
        <TotalContributionsAmt>RESTRICTED</TotalContributionsAmt>
      </ContributorInformationGrp>
    </IRS990ScheduleB>
    <IRS990ScheduleD documentId="IRS990ScheduleD" softwareId="16000303" softwareVersionNum="2016v3.0">
      <FundsAndOtherAccountsHeldCnt>1</FundsAndOtherAccountsHeldCnt>
      <FundsAndOtherAccountsVlEOYAmt>1983264</FundsAndOtherAccountsVlEOYAmt>
      <DisclosedOrgLegCtrlInd>false</DisclosedOrgLegCtrlInd>
      <DisclosedForCharitablePrpsInd>true</DisclosedForCharitablePrpsInd>
      <CYEndwmtFundGrp>
        <BeginningYearBalanceAmt>1862301</BeginningYearBalanceAmt>
        <InvestmentEarningsOrLossesAmt>175408</InvestmentEarningsOrLossesAmt>
        <GrantsOrScholarshipsAmt>37000</GrantsOrScholarshipsAmt>
        <AdministrativeExpensesAmt>17445</AdministrativeExpensesAmt>
        <EndYearBalanceAmt>1983264</EndYearBalanceAmt>
      </CYEndwmtFundGrp>
      <CYMinus1YrEndwmtFundGrp>
        <BeginningYearBalanceAmt>1899680</BeginningYearBalanceAmt>
        <InvestmentEarningsOrLossesAmt>16255</InvestmentEarningsOrLossesAmt>
        <GrantsOrScholarshipsAmt>36000</GrantsOrScholarshipsAmt>
        <AdministrativeExpensesAmt>17634</AdministrativeExpensesAmt>
        <EndYearBalanceAmt>1862301</EndYearBalanceAmt>
      </CYMinus1YrEndwmtFundGrp>
      <CYMinus2YrEndwmtFundGrp>
        <BeginningYearBalanceAmt>1820923</BeginningYearBalanceAmt>
        <InvestmentEarningsOrLossesAmt>132116</InvestmentEarningsOrLossesAmt>
        <GrantsOrScholarshipsAmt>36500</GrantsOrScholarshipsAmt>
        <AdministrativeExpensesAmt>16859</AdministrativeExpensesAmt>
        <EndYearBalanceAmt>1899680</EndYearBalanceAmt>
      </CYMinus2YrEndwmtFundGrp>
      <CYMinus3YrEndwmtFundGrp>
        <BeginningYearBalanceAmt>1715800</BeginningYearBalanceAmt>
        <InvestmentEarningsOrLossesAmt>147792</InvestmentEarningsOrLossesAmt>
        <GrantsOrScholarshipsAmt>28059</GrantsOrScholarshipsAmt>
        <AdministrativeExpensesAmt>14610</AdministrativeExpensesAmt>
        <EndYearBalanceAmt>1820923</EndYearBalanceAmt>
      </CYMinus3YrEndwmtFundGrp>
      <CYMinus4YrEndwmtFundGrp>
        <ContributionsAmt>1711472</ContributionsAmt>
        <InvestmentEarningsOrLossesAmt>30210</InvestmentEarningsOrLossesAmt>
        <GrantsOrScholarshipsAmt>21900</GrantsOrScholarshipsAmt>
        <AdministrativeExpensesAmt>3982</AdministrativeExpensesAmt>
        <EndYearBalanceAmt>1715800</EndYearBalanceAmt>
      </CYMinus4YrEndwmtFundGrp>
      <PrmnntEndowmentBalanceEOYPct>0.75000</PrmnntEndowmentBalanceEOYPct>
      <TermEndowmentBalanceEOYPct>0.25000</TermEndowmentBalanceEOYPct>
      <EndowmentsHeldUnrelatedOrgInd>false</EndowmentsHeldUnrelatedOrgInd>
      <EndowmentsHeldRelatedOrgInd>false</EndowmentsHeldRelatedOrgInd>
      <RelatedOrgListSchRInd>false</RelatedOrgListSchRInd>
      <LandGrp>
        <OtherCostOrOtherBasisAmt>1928095</OtherCostOrOtherBasisAmt>
        <BookValueAmt>1928095</BookValueAmt>
      </LandGrp>
      <BuildingsGrp>
        <OtherCostOrOtherBasisAmt>18582739</OtherCostOrOtherBasisAmt>
        <DepreciationAmt>7391989</DepreciationAmt>
        <BookValueAmt>11190750</BookValueAmt>
      </BuildingsGrp>
      <LeaseholdImprovementsGrp>
        <OtherCostOrOtherBasisAmt>1834205</OtherCostOrOtherBasisAmt>
        <DepreciationAmt>787953</DepreciationAmt>
        <BookValueAmt>1046252</BookValueAmt>
      </LeaseholdImprovementsGrp>
      <EquipmentGrp>
        <OtherCostOrOtherBasisAmt>2121275</OtherCostOrOtherBasisAmt>
        <DepreciationAmt>1293464</DepreciationAmt>
        <BookValueAmt>827811</BookValueAmt>
      </EquipmentGrp>
      <OtherLandBuildingsGrp>
        <OtherCostOrOtherBasisAmt>107409</OtherCostOrOtherBasisAmt>
        <DepreciationAmt>100551</DepreciationAmt>
        <BookValueAmt>6858</BookValueAmt>
      </OtherLandBuildingsGrp>
      <TotalBookValueLandBuildingsAmt>14999766</TotalBookValueLandBuildingsAmt>
      <OtherLiabilitiesOrgGrp>
        <Desc>Interest rate swap agreements</Desc>
        <Amt>131541</Amt>
      </OtherLiabilitiesOrgGrp>
      <TotalLiabilityAmt>131541</TotalLiabilityAmt>
      <SupplementalInformationDetail>
        <FormAndLineReferenceDesc>Part V, Line 4: Intended uses of the endowment fund.</FormAndLineReferenceDesc>
        <ExplanationTxt>ENDOWMENT FUNDS WERE SET ASIDE FOR SCHOLARSHIP GRANTS IN SUPPORT OF DELPHI SCHOOLS, INC. STUDENTS.</ExplanationTxt>
      </SupplementalInformationDetail>
    </IRS990ScheduleD>
    <IRS990ScheduleE documentId="IRS990ScheduleE" softwareId="16000303" softwareVersionNum="2016v3.0">
      <NondiscriminatoryPolicyStmtInd>true</NondiscriminatoryPolicyStmtInd>
      <PolicyStmtInBrochuresEtcInd>true</PolicyStmtInBrochuresEtcInd>
      <PlcyPblczdViaBroadcastMediaInd>true</PlcyPblczdViaBroadcastMediaInd>
      <MaintainRacialCompRecsInd>true</MaintainRacialCompRecsInd>
      <MaintainScholarshipsRecsInd>true</MaintainScholarshipsRecsInd>
      <MaintainCpyOfBrochuresEtcInd>true</MaintainCpyOfBrochuresEtcInd>
      <MaintainCpyOfAllSolInd>true</MaintainCpyOfAllSolInd>
      <DiscriminateRaceStdntsRghtsInd>false</DiscriminateRaceStdntsRghtsInd>
      <DiscriminateRaceAdmissPlcyInd>false</DiscriminateRaceAdmissPlcyInd>
      <DiscriminateRaceEmplmFcultyInd>false</DiscriminateRaceEmplmFcultyInd>
      <DiscriminateRaceSchsInd>false</DiscriminateRaceSchsInd>
      <DiscriminateRaceEducPlcyInd>false</DiscriminateRaceEducPlcyInd>
      <DiscriminateRaceUseOfFcltsInd>false</DiscriminateRaceUseOfFcltsInd>
      <DiscriminateRaceAthltProgInd>false</DiscriminateRaceAthltProgInd>
      <DiscriminateRaceOtherActyInd>false</DiscriminateRaceOtherActyInd>
      <GovernmentFinancialAidRcvdInd>false</GovernmentFinancialAidRcvdInd>
      <GovernmentFinancialAidRvkdInd>false</GovernmentFinancialAidRvkdInd>
      <ComplianceWithRevProc7550Ind>true</ComplianceWithRevProc7550Ind>
      <SupplementalInformationDetail>
        <FormAndLineReferenceDesc>Schedule E, Line 3 - Racially Nondiscriminatory Policy Publicized</FormAndLineReferenceDesc>
        <ExplanationTxt>THE ORGANIZATION HAS PUBLISHED NOTICE STATING ITS RACIALLY NONDISCRIMINATORY POLICY IN THE REQUIRED FORM, IN NEWSPAPERS OF GENERAL CIRCULATION, AND AT LEAST ONCE ANNUALLY (BUT IN ALL EVENTS, DURING ITS REGISTRATION PERIODS).</ExplanationTxt>
      </SupplementalInformationDetail>
      <SupplementalInformationDetail>
        <FormAndLineReferenceDesc>Schedule E, Line 4 - Explanation of Records and Materials Not Maintained</FormAndLineReferenceDesc>
      </SupplementalInformationDetail>
      <SupplementalInformationDetail>
        <FormAndLineReferenceDesc>Schedule E, Line 5 - Explanation of Organization Discrimination by Race</FormAndLineReferenceDesc>
      </SupplementalInformationDetail>
    </IRS990ScheduleE>
    <IRS990ScheduleG documentId="IRS990ScheduleG" softwareId="16000303" softwareVersionNum="2016v3.0">
      <AgrmtProfFundraisingActyInd>false</AgrmtProfFundraisingActyInd>
      <FundraisingEventInformationGrp>
        <Event1Nm>Game Night</Event1Nm>
        <GrossReceiptsEvent1Amt>12674</GrossReceiptsEvent1Amt>
        <CharitableContriEvent1Amt>12674</CharitableContriEvent1Amt>
        <NonCashPrizesEvent1Amt>470</NonCashPrizesEvent1Amt>
        <FoodAndBeverageEvent1Amt>837</FoodAndBeverageEvent1Amt>
        <Event2Nm>Duck Splash</Event2Nm>
        <GrossReceiptsEvent2Amt>11350</GrossReceiptsEvent2Amt>
        <CharitableContriEvent2Amt>11350</CharitableContriEvent2Amt>
        <NonCashPrizesEvent2Amt>900</NonCashPrizesEvent2Amt>
        <OtherEventsTotalCnt>1</OtherEventsTotalCnt>
        <GrossReceiptsOtherEventsAmt>6097</GrossReceiptsOtherEventsAmt>
        <CharitableContriOtherEventsAmt>6097</CharitableContriOtherEventsAmt>
        <GrossReceiptsTotalAmt>30121</GrossReceiptsTotalAmt>
        <CharitableContributionsTotAmt>30121</CharitableContributionsTotAmt>
        <NonCashPrizesTotalEventsAmt>1370</NonCashPrizesTotalEventsAmt>
        <FoodAndBeverageTotalEventsAmt>837</FoodAndBeverageTotalEventsAmt>
        <DirectExpenseSummaryEventsAmt>2207</DirectExpenseSummaryEventsAmt>
        <NetIncomeSummaryAmt>-2207</NetIncomeSummaryAmt>
      </FundraisingEventInformationGrp>
    </IRS990ScheduleG>
    <IRS990ScheduleI documentId="IRS990ScheduleI" softwareId="16000303" softwareVersionNum="2016v3.0">
      <GrantRecordsMaintainedInd>true</GrantRecordsMaintainedInd>
      <RecipientTable>
        <RecipientBusinessName>
          <BusinessNameLine1Txt>Competent Education Services</BusinessNameLine1Txt>
        </RecipientBusinessName>
        <USAddress>
          <AddressLine1Txt>1 West Campbell Avenue A110</AddressLine1Txt>
          <CityNm>Campbell</CityNm>
          <StateAbbreviationCd>CA</StateAbbreviationCd>
          <ZIPCd>95008</ZIPCd>
        </USAddress>
        <RecipientEIN>472247461</RecipientEIN>
        <IRCSectionDesc>3</IRCSectionDesc>
        <CashGrantAmt>329894</CashGrantAmt>
        <NonCashAssistanceAmt>45016</NonCashAssistanceAmt>
        <ValuationMethodUsedDesc>book value</ValuationMethodUsedDesc>
        <NonCashAssistanceDesc>See supporting detail statement</NonCashAssistanceDesc>
        <PurposeOfGrantTxt>To affiliate school upon separation</PurposeOfGrantTxt>
      </RecipientTable>
      <Total501c3OrgCnt>0</Total501c3OrgCnt>
      <TotalOtherOrgCnt>1</TotalOtherOrgCnt>
      <GrantsOtherAsstToIndivInUSGrp>
        <GrantTypeTxt>Scholarships to individuals</GrantTypeTxt>
        <RecipientCnt>282</RecipientCnt>
        <CashGrantAmt>119964</CashGrantAmt>
        <NonCashAssistanceAmt>2236429</NonCashAssistanceAmt>
        <ValuationMethodUsedDesc>Cost</ValuationMethodUsedDesc>
        <NonCashAssistanceDesc>Tuition reduction</NonCashAssistanceDesc>
      </GrantsOtherAsstToIndivInUSGrp>
      <SupplementalInformationDetail>
        <FormAndLineReferenceDesc>Grantmaker's Description of How Grants are Used</FormAndLineReferenceDesc>
        <ExplanationTxt>Fellowships, Scholarships, and Financial Aid programs are initially analyzed by the nationally-accredited company FAST (Financial Aid for School Tuition); but are ultimately only awarded based on merit and/or need. All programs are administered pursuant to directives approved by the Board of Directors and are reviewed regularly by administrative staff and the Board of Directors. Funds awarded are accounted for as a reduction in tuition otherwise required under signed enrollment contracts.</ExplanationTxt>
      </SupplementalInformationDetail>
    </IRS990ScheduleI>
    <IRS990ScheduleJ documentId="IRS990ScheduleJ" softwareId="16000303" softwareVersionNum="2016v3.0">
      <HousingAllowanceOrResidenceInd>X</HousingAllowanceOrResidenceInd>
      <WrittenPolicyRefTAndEExpnssInd>false</WrittenPolicyRefTAndEExpnssInd>
      <SubstantiationRequiredInd>true</SubstantiationRequiredInd>
      <IndependentConsultantInd>X</IndependentConsultantInd>
      <CompensationSurveyInd>X</CompensationSurveyInd>
      <BoardOrCommitteeApprovalInd>X</BoardOrCommitteeApprovalInd>
      <SeverancePaymentInd>false</SeverancePaymentInd>
      <SupplementalNonqualRtrPlanInd>false</SupplementalNonqualRtrPlanInd>
      <EquityBasedCompArrngmInd>false</EquityBasedCompArrngmInd>
      <CompBasedOnRevenueOfFlngOrgInd>false</CompBasedOnRevenueOfFlngOrgInd>
      <CompBsdOnRevRelatedOrgsInd>false</CompBsdOnRevRelatedOrgsInd>
      <CompBsdNetEarnsFlngOrgInd>false</CompBsdNetEarnsFlngOrgInd>
      <CompBsdNetEarnsRltdOrgsInd>false</CompBsdNetEarnsRltdOrgsInd>
      <AnyNonFixedPaymentsInd>false</AnyNonFixedPaymentsInd>
      <InitialContractExceptionInd>false</InitialContractExceptionInd>
      <RebuttablePresumptionProcInd>false</RebuttablePresumptionProcInd>
      <RltdOrgOfficerTrstKeyEmplGrp>
        <PersonNm>Alan Rothe</PersonNm>
        <TitleTxt>Exec Vice Pres</TitleTxt>
        <BaseCompensationFilingOrgAmt>108835</BaseCompensationFilingOrgAmt>
        <BonusFilingOrganizationAmount>43315</BonusFilingOrganizationAmount>
        <OtherCompensationFilingOrgAmt>8493</OtherCompensationFilingOrgAmt>
        <NontaxableBenefitsFilingOrgAmt>21876</NontaxableBenefitsFilingOrgAmt>
        <TotalCompensationFilingOrgAmt>182519</TotalCompensationFilingOrgAmt>
      </RltdOrgOfficerTrstKeyEmplGrp>
      <RltdOrgOfficerTrstKeyEmplGrp>
        <PersonNm>Gregory Ott</PersonNm>
        <TitleTxt>President</TitleTxt>
        <BaseCompensationFilingOrgAmt>133031</BaseCompensationFilingOrgAmt>
        <BonusFilingOrganizationAmount>106983</BonusFilingOrganizationAmount>
        <NontaxableBenefitsFilingOrgAmt>21682</NontaxableBenefitsFilingOrgAmt>
        <TotalCompensationFilingOrgAmt>261696</TotalCompensationFilingOrgAmt>
      </RltdOrgOfficerTrstKeyEmplGrp>
      <RltdOrgOfficerTrstKeyEmplGrp>
        <PersonNm>John Nosko</PersonNm>
        <TitleTxt>Sec &amp; Treasurer</TitleTxt>
        <BaseCompensationFilingOrgAmt>105540</BaseCompensationFilingOrgAmt>
        <BonusFilingOrganizationAmount>48040</BonusFilingOrganizationAmount>
        <NontaxableBenefitsFilingOrgAmt>16155</NontaxableBenefitsFilingOrgAmt>
        <TotalCompensationFilingOrgAmt>169735</TotalCompensationFilingOrgAmt>
      </RltdOrgOfficerTrstKeyEmplGrp>
      <SupplementalInformationDetail>
        <FormAndLineReferenceDesc>Part I, Line 1a: Relevant information in regards to selections on 1a.</FormAndLineReferenceDesc>
        <ExplanationTxt>A majority of Delphi Schools, Inc.'s employees at the Oregon boarding school are required to accept room and board on its premises as a condition of their employment. Section 199 of the Internal Revenue Code of 1986 excludes the value of such room and board from the taxable gross income of the employees. The value thereof is reported as the employees' non-taxable benefits on Form 990. Neither a written policy nor substantiation is required, since no cash allowances related thereto are provided to the employees.</ExplanationTxt>
      </SupplementalInformationDetail>
      <SupplementalInformationDetail>
        <FormAndLineReferenceDesc>Part I, Line 1b: Reason for not following policy regarding payment provisions for expenses</FormAndLineReferenceDesc>
        <ExplanationTxt>See Part 1 line 1A</ExplanationTxt>
      </SupplementalInformationDetail>
    </IRS990ScheduleJ>
    <IRS990ScheduleK documentId="IRS990ScheduleK.1" softwareId="16000303" softwareVersionNum="2016v3.0">
      <TaxExemptBondsIssuesGrp>
        <BondReferenceCd>A</BondReferenceCd>
        <IssuerName>
          <BusinessNameLine1Txt>California Statewide Comm</BusinessNameLine1Txt>
        </IssuerName>
        <BondIssuerEIN>521598225</BondIssuerEIN>
        <BondIssuedDt>2012-08-30</BondIssuedDt>
        <IssuePriceAmt>4839600</IssuePriceAmt>
        <PurposeDesc>Re-finance</PurposeDesc>
      </TaxExemptBondsIssuesGrp>
      <TaxExemptBondsProceedsGrp>
        <BondReferenceCd>A</BondReferenceCd>
        <RefundingEscrowAmt>4765800</RefundingEscrowAmt>
        <IssuanceCostsFromProceedsAmt>124765</IssuanceCostsFromProceedsAmt>
        <CurrentRefundingInd>true</CurrentRefundingInd>
        <AdvanceRefundingInd>false</AdvanceRefundingInd>
        <FinalAllocationMadeInd>true</FinalAllocationMadeInd>
        <AdequateBooksAndRecMaintInd>true</AdequateBooksAndRecMaintInd>
      </TaxExemptBondsProceedsGrp>
      <TaxExemptBondsPrivateBusUseGrp>
        <BondReferenceCd>A</BondReferenceCd>
        <OwningBondFinancedPropertyInd>false</OwningBondFinancedPropertyInd>
        <AnyLeaseArrangementsInd>false</AnyLeaseArrangementsInd>
        <MgmtContractBondFincdPropInd>false</MgmtContractBondFincdPropInd>
        <AnyResearchAgreementsInd>false</AnyResearchAgreementsInd>
        <BondIssMeetPrvtSecPymtTestInd>true</BondIssMeetPrvtSecPymtTestInd>
        <ChangeInUseBondFinancedPropInd>false</ChangeInUseBondFinancedPropInd>
        <ProcsNonqualifiedBondRemdtdInd>true</ProcsNonqualifiedBondRemdtdInd>
      </TaxExemptBondsPrivateBusUseGrp>
    </IRS990ScheduleK>
    <IRS990ScheduleL documentId="IRS990ScheduleL" softwareId="16000303" softwareVersionNum="2016v3.0">
      <BusTrInvolveInterestedPrsnGrp>
        <NameOfInterested>
          <PersonNm>Julie Nosko</PersonNm>
        </NameOfInterested>
        <RelationshipDescriptionTxt>Ofcr\Dir Spouse</RelationshipDescriptionTxt>
        <TransactionAmt>106244</TransactionAmt>
        <TransactionDesc>Employment</TransactionDesc>
        <SharingOfRevenuesInd>false</SharingOfRevenuesInd>
      </BusTrInvolveInterestedPrsnGrp>
      <BusTrInvolveInterestedPrsnGrp>
        <NameOfInterested>
          <PersonNm>April Denny Ott</PersonNm>
        </NameOfInterested>
        <RelationshipDescriptionTxt>Ofcr\Dir Spouse</RelationshipDescriptionTxt>
        <TransactionAmt>75357</TransactionAmt>
        <TransactionDesc>Employment</TransactionDesc>
        <SharingOfRevenuesInd>false</SharingOfRevenuesInd>
      </BusTrInvolveInterestedPrsnGrp>
      <BusTrInvolveInterestedPrsnGrp>
        <NameOfInterested>
          <PersonNm>Nowell Didear</PersonNm>
        </NameOfInterested>
        <RelationshipDescriptionTxt>Ofcr\Dir Spouse</RelationshipDescriptionTxt>
        <TransactionAmt>11180</TransactionAmt>
        <TransactionDesc>Employment</TransactionDesc>
        <SharingOfRevenuesInd>false</SharingOfRevenuesInd>
      </BusTrInvolveInterestedPrsnGrp>
      <BusTrInvolveInterestedPrsnGrp>
        <NameOfInterested>
          <PersonNm>Joelle Rothe</PersonNm>
        </NameOfInterested>
        <RelationshipDescriptionTxt>Ofcr\Dir Spouse</RelationshipDescriptionTxt>
        <TransactionAmt>71770</TransactionAmt>
        <TransactionDesc>Employment</TransactionDesc>
        <SharingOfRevenuesInd>false</SharingOfRevenuesInd>
      </BusTrInvolveInterestedPrsnGrp>
      <BusTrInvolveInterestedPrsnGrp>
        <NameOfInterested>
          <PersonNm>Melissa McPhail</PersonNm>
        </NameOfInterested>
        <RelationshipDescriptionTxt>Director Spouse</RelationshipDescriptionTxt>
        <TransactionAmt>78131</TransactionAmt>
        <TransactionDesc>Employment</TransactionDesc>
        <SharingOfRevenuesInd>false</SharingOfRevenuesInd>
      </BusTrInvolveInterestedPrsnGrp>
      <BusTrInvolveInterestedPrsnGrp>
        <NameOfInterested>
          <PersonNm>Kelly Olivares</PersonNm>
        </NameOfInterested>
        <RelationshipDescriptionTxt>Ofcr/Dir Child</RelationshipDescriptionTxt>
        <TransactionAmt>75111</TransactionAmt>
        <TransactionDesc>Employment</TransactionDesc>
        <SharingOfRevenuesInd>false</SharingOfRevenuesInd>
      </BusTrInvolveInterestedPrsnGrp>
      <BusTrInvolveInterestedPrsnGrp>
        <NameOfInterested>
          <PersonNm>Adam Whitworth</PersonNm>
        </NameOfInterested>
        <RelationshipDescriptionTxt>Ofcr/Dir Child</RelationshipDescriptionTxt>
        <TransactionAmt>33642</TransactionAmt>
        <TransactionDesc>Employment</TransactionDesc>
        <SharingOfRevenuesInd>false</SharingOfRevenuesInd>
      </BusTrInvolveInterestedPrsnGrp>
      <BusTrInvolveInterestedPrsnGrp>
        <NameOfInterested>
          <PersonNm>Alyssa Whitworth</PersonNm>
        </NameOfInterested>
        <RelationshipDescriptionTxt>Ofcr/Dir Child</RelationshipDescriptionTxt>
        <TransactionAmt>32201</TransactionAmt>
        <TransactionDesc>Employment</TransactionDesc>
        <SharingOfRevenuesInd>false</SharingOfRevenuesInd>
      </BusTrInvolveInterestedPrsnGrp>
      <SupplementalInformationDetail>
        <FormAndLineReferenceDesc>Schedule L, Part V Supplemental Information</FormAndLineReferenceDesc>
        <ExplanationTxt>Julie Nosko Business ManagerApril Denny Ott RegistrarNowell Didear DevelopmentJoelle Rothe TeacherMelissa McPhail Director of MarketingKelly Olivares Medical LiaisonAdam Whitworth TeacherAlyssa Whitworth TeacherThe transaction amount in column (c) consists of cash compensation and the fair market value of non-taxable benefits which may include tuition remission, housing, Section 125 contributions,and employer paid health insurance.</ExplanationTxt>
      </SupplementalInformationDetail>
    </IRS990ScheduleL>
    <IRS990ScheduleO documentId="IRS990ScheduleO" softwareId="16000303" softwareVersionNum="2016v3.0">
      <SupplementalInformationDetail>
        <FormAndLineReferenceDesc>Form 990, Part VI, Line 2: Description of Business or Family Relationship of Officers, Directors, Et</FormAndLineReferenceDesc>
        <ExplanationTxt>See Schedule L Part IV</ExplanationTxt>
      </SupplementalInformationDetail>
      <SupplementalInformationDetail>
        <FormAndLineReferenceDesc>Form 990, Part VI, Line 11b: Form 990 Review Process</FormAndLineReferenceDesc>
        <ExplanationTxt>The Form 990 is reviewed by the corporation's management and board of directors.</ExplanationTxt>
      </SupplementalInformationDetail>
      <SupplementalInformationDetail>
        <FormAndLineReferenceDesc>Form 990, Part VI, Line 12c: Explanation of Monitoring and Enforcement of Conflicts</FormAndLineReferenceDesc>
        <ExplanationTxt>DELPHI SCHOOLS, INC., HAS A CONFLICTS-OF-INTEREST POLICY AND A WHISTLE BLOWER POLICY, WHICH TOGETHER ENSURE THAT ANY MEMBER OF THE CORPORATION'S BOARD OF DIRECTORS (OR ANY COMMITTEE OF THE BOARD OF DIRECTORS), AND/OR ANY OFFICER, EMPLOYEE, FIDUCIARY, OR AGENT OF THE CORPORATION (COLLECTIVELY "INTERESTED PERSON"), WHO HAS A DIRECT OR INDIRECT FINANCIAL INTEREST (A DEFINED TERM, WHICH INCLUDES ALL CIRCUMSTANCES IN WHICH AN INTERESTED PERSON MAY PROFIT FROM AN ACTION OR DECISION BY THE CORPORATION IN WHICH THE INTERESTED PERSONNEL PARTICIPATES, AND OF WHICH HE OR SHE HAS KNOWLEDGE) IN A TRANSACTION OR ACTIVITY, DISCLOSES THE EXISTENCE OF THE FINANCIAL INTEREST. SUCH DISCLOSURE MUST BE MADE TO THE BOARD OF DIRECTORS (OR IT'S APPROPRIATE COMMITTEE) WHICH, IN TURN, MUST MAKE A DECISION ON WHETHER A CONFLICT EXISTS, AND IF IT DOES, WHETHER THE SUBJECT TRANSACTION OR ACTIVITY IS IN THE CORPORATION'S BEST INTEREST, IS FOR THE CORPORATION'S BENEFIT, AND IS FAIR AND REASONABLE. VIOLATIONS RESULT IN APPROPRIATE DISCIPLINARY AND CORRECTIVE ACTION. ALL OFFICERS, BOARD MEMBERS, AND KEY PERSONNEL SIGN ANNUAL STATEMENTS ATTESTING TO THEIR COMPLIANCE WITH THE CORPORATION'S CONFLICTS-OF-INTEREST POLICY. ALL MEMBERS OF THE BOARD OF DIRECTORS, AND ALL OFFICERS, EMPLOYEES, FIDUCIARIES, AND AGENTS OF THE CORPORATION, ARE ALSO PROVIDED WITH A COPY OF THE CORPORATION'S CONFLICTS-OF-INTEREST POLICY AND WHISTLE BLOWER POLICY.</ExplanationTxt>
      </SupplementalInformationDetail>
      <SupplementalInformationDetail>
        <FormAndLineReferenceDesc>Form 990, Part VI, Line 15b: Compensation Review and Approval Process for Officers and Key Employees</FormAndLineReferenceDesc>
        <ExplanationTxt>DELPHI SCHOOLS, INC., HAS A COMPENSATION POLICY THAT ENSURES AGAINST PAYMENTS IN EXCESS OF REASONABLE COMPENSATION TO ITS OFFICERS, DIRECTORS, AND KEY EMPLOYEES -- THAT IS, AGAINST PAYMENTS IN EXCESS OF COMPENSATION AMOUNTS THAT WOULD ORDINARILY BE PAID FOR LIKE SERVICES BY A LIKE ORGANIZATION UNDER LIKE CIRCUMSTANCES. IN ADDITION, THE CORPORATION'S CONFLICTS-OF-INTEREST POLICY REQUIRES PERIODIC REVIEW BY THE BOARD OF DIRECTORS TO ENSURE THAT COMPENSATION ARRANGEMENTS AND BENEFITS FOR THE CORPORATION'S OFFICERS, DIRECTORS, AND KEY EMPLOYEES DO NOT EXCEED LEVELS THAT ARE REASONABLE, BASED ON INDEPENDENT COMPENSATION CONSULTANT'S WRITTEN ANALYSIS, INDEPENDENT LEGAL COUNSEL REVIEW, AND ARM'S-LENGTH BARGAINING.THE COMPENSATION REVIEW PROCESS DESCRIBED ABOVE WAS COMPLETED IN 2014 FOR GREGORY OTT, ROSEMARY DIDEAR, JOHN NOSKO, AND ALAN ROTHE.</ExplanationTxt>
      </SupplementalInformationDetail>
      <SupplementalInformationDetail>
        <FormAndLineReferenceDesc>Form 990, Part VI, Line 19: Other Organization Documents Publicly Available</FormAndLineReferenceDesc>
        <ExplanationTxt>Delphi Schools, Inc., makes its governing documents, conflicts-of-interest policy, and/or financial statements available to the public only as required by Federal and State law.</ExplanationTxt>
      </SupplementalInformationDetail>
    </IRS990ScheduleO>
  </ReturnData>
</Return>